cloud_regions_info/__init__.py
cloud_regions_info/core.py
cloud_regions_info/mappings/alibaba_regions.json
cloud_regions_info/mappings/aws_regions.json
cloud_regions_info/mappings/azure_regions.json
cloud_regions_info/mappings/digitalocean_regions.json
cloud_regions_info/mappings/gcp_regions.json
cloud_regions_info/mappings/ibm_regions.json
cloud_regions_info/mappings/linode_regions.json
cloud_regions_info/mappings/oci_regions.json
cloud_regions_info/mappings/onedrive_regions.json
cloud_regions_info/mappings/vultr_regions.json
cloud_regions_info/models.py
cloud_regions_info/providers/__init__.py
cloud_regions_info/providers/alibaba.py
cloud_regions_info/providers/aws.py
cloud_regions_info/providers/azure.py
cloud_regions_info/providers/base.py
cloud_regions_info/providers/digitalocean.py
cloud_regions_info/providers/gcp.py
cloud_regions_info/providers/ibm.py
cloud_regions_info/providers/oci.py
cloud_regions_info/providers/onedrive.py
cloud_regions_info/providers/vultr.py
cloud_regions_info-1.0.1.dist-info/LICENSE
cloud_regions_info-1.0.1.dist-info/METADATA
cloud_regions_info-1.0.1.dist-info/WHEEL
cloud_regions_info-1.0.1.dist-info/RECORD
