Metadata-Version: 2.1
Name: cloud-regions-info
Version: 1.0.1
Summary: A Python package for retrieving detailed cloud region information across AWS, Azure, GCP, and other cloud providers.
License: MIT
Author: Ditikrushna Giri
Author-email: ping@ditikrushna.xyz
Requires-Python: >=3.10,<3.13
Classifier: License :: OSI Approved :: MIT License
Classifier: Programming Language :: Python :: 3
Classifier: Programming Language :: Python :: 3.10
Classifier: Programming Language :: Python :: 3.11
Requires-Dist: pydantic (==1.10.5)
